MANIFEST.in
README.rst
VERSION
setup.py
hitchserve/__init__.py
hitchserve/hitch_dir.py
hitchserve/hitch_exception.py
hitchserve/hitch_service.py
hitchserve/service_bundle.py
hitchserve/service_engine.py
hitchserve/service_handle.py
hitchserve/service_logs.py
hitchserve/test_engine.py
hitchserve/utils.py
hitchserve.egg-info/PKG-INFO
hitchserve.egg-info/SOURCES.txt
hitchserve.egg-info/dependency_links.txt
hitchserve.egg-info/not-zip-safe
hitchserve.egg-info/requires.txt
hitchserve.egg-info/top_level.txt